atoti/LICENSE
atoti/__init__.py
atoti/__resources__/api.json
atoti/__resources__/app-extensions/@activeviam/advanced-extension/extensionEntry.js
atoti/__resources__/app-extensions/@activeviam/advanced-extension/manifest.json
atoti/__resources__/app-extensions/@activeviam/advanced-extension/static/js/async/738.00d3e768.js
atoti/__resources__/app-extensions/@activeviam/advanced-extension/static/js/async/999.8240f2e1.js
atoti/__resources__/app-extensions/@activeviam/advanced-extension/static/js/index.94278bde.js
atoti/__resources__/app-extensions/@atoti/branding-app-extension/extensionEntry.js
atoti/__resources__/app-extensions/@atoti/branding-app-extension/manifest.json
atoti/__resources__/app-extensions/@atoti/branding-app-extension/static/js/async/272.6d22b758.js
atoti/__resources__/app-extensions/@atoti/branding-app-extension/static/js/index.69b07b86.js
atoti/__resources__/atoti-server-version.txt
atoti/__resources__/tutorial/data/products.csv
atoti/__resources__/tutorial/data/sales.csv
atoti/__resources__/tutorial/data/shops.csv
atoti/__resources__/tutorial/images/cube-concept.svg
atoti/__resources__/tutorial/images/cumulative-amount-per-scenario.gif
atoti/__resources__/tutorial/images/cumulative-amount.png
atoti/__resources__/tutorial/images/donut-chart.png
atoti/__resources__/tutorial/images/drilldown.gif
atoti/__resources__/tutorial/images/drilldown.svg
atoti/__resources__/tutorial/images/filter-chart.gif
atoti/__resources__/tutorial/images/first-chart.gif
atoti/__resources__/tutorial/images/first-pivot-table.gif
atoti/__resources__/tutorial/images/grand-total.svg
atoti/__resources__/tutorial/images/margin-rate-per-scenario.gif
atoti/__resources__/tutorial/images/percent-of-parent.gif
atoti/__resources__/tutorial/images/pivot-table.svg
atoti/__resources__/tutorial/images/price-per-category.png
atoti/__resources__/tutorial/images/save-in-app.gif
atoti/__resources__/tutorial/images/scenarios-matrix.gif
atoti/__resources__/tutorial/images/slice-and-dice.svg
atoti_client-0.9.12.dist-info/WHEEL
atoti_client-0.9.12.dist-info/METADATA
atoti_client-0.9.12.dist-info/RECORD
