Metadata-Version: 2.3
Name: atoti-client
Version: 0.9.12
Summary: Code to interact with an Atoti session
Author: ActiveViam
Author-email: ActiveViam <atoti-dev@activeviam.com>
Classifier: Development Status :: 4 - Beta
Classifier: License :: Free for non-commercial use
Classifier: Operating System :: OS Independent
Classifier: Programming Language :: Python :: 3
Classifier: Topic :: Scientific/Engineering :: Information Analysis
Classifier: Topic :: Scientific/Engineering :: Visualization
Classifier: Typing :: Typed
Requires-Dist: atoti-core==0.9.12
Requires-Dist: graphql-core>=3.2.6
Requires-Dist: httpx>=0.28.1,<1.0.dev1
Requires-Dist: numpy>=2.2.6
Requires-Dist: pandas>=2.2.3,<3.0.0rc0
Requires-Dist: py4j>=0.10.9.7
Requires-Dist: pyarrow>=21.0.0
Requires-Dist: pydantic>=2.12.3
Requires-Dist: typing-extensions>=4.15.0
Requires-Dist: atoti-client-aws==0.9.12 ; extra == 'aws'
Requires-Dist: atoti-client-azure==0.9.12 ; extra == 'azure'
Requires-Dist: atoti-client-directquery-bigquery==0.9.12 ; extra == 'directquery-bigquery'
Requires-Dist: atoti-client-directquery-clickhouse==0.9.12 ; extra == 'directquery-clickhouse'
Requires-Dist: atoti-client-directquery-databricks==0.9.12 ; extra == 'directquery-databricks'
Requires-Dist: atoti-client-directquery-jdbc==0.9.12 ; extra == 'directquery-jdbc'
Requires-Dist: atoti-client-directquery-mssql==0.9.12 ; extra == 'directquery-mssql'
Requires-Dist: atoti-client-directquery-redshift==0.9.12 ; extra == 'directquery-redshift'
Requires-Dist: atoti-client-directquery-snowflake==0.9.12 ; extra == 'directquery-snowflake'
Requires-Dist: atoti-client-directquery-synapse==0.9.12 ; extra == 'directquery-synapse'
Requires-Dist: atoti-client-gcp==0.9.12 ; extra == 'gcp'
Requires-Dist: atoti-client-jdbc==0.9.12 ; extra == 'jdbc'
Requires-Dist: atoti-jupyterlab==0.9.12 ; extra == 'jupyterlab'
Requires-Dist: atoti-client-kafka==0.9.12 ; extra == 'kafka'
Requires-Python: >=3.10
Project-URL: Documentation, https://docs.activeviam.com/products/atoti/python-sdk/0.9.12/api/atoti.html
Project-URL: Homepage, https://www.atoti.io
Project-URL: Issues, https://github.com/atoti/atoti/issues
Provides-Extra: aws
Provides-Extra: azure
Provides-Extra: directquery-bigquery
Provides-Extra: directquery-clickhouse
Provides-Extra: directquery-databricks
Provides-Extra: directquery-jdbc
Provides-Extra: directquery-mssql
Provides-Extra: directquery-redshift
Provides-Extra: directquery-snowflake
Provides-Extra: directquery-synapse
Provides-Extra: gcp
Provides-Extra: jdbc
Provides-Extra: jupyterlab
Provides-Extra: kafka
